[
  {
    "slug": "facebook-double-u-casino",
    "type": "post",
    "title": "Facebook Double U Casino (What It Is, How It Works & Is It Real Gambling?)",
    "date": "2025-12-16T17:05:30.671Z",
    "modified": "2025-12-16T17:05:30.671Z"
  },
  {
    "slug": "best-online-casino-fast-payout-usa",
    "type": "post",
    "title": "Best Online Casino Fast Payout USA (2025 Guide to Quick Withdrawals)",
    "date": "2025-12-16T16:54:46.369Z",
    "modified": "2025-12-16T16:54:46.369Z"
  },
  {
    "slug": "is-betmgm-casino-legit",
    "type": "post",
    "title": "Is BetMGM Casino Legit? (2025 Legal, Safety & Trust Review)",
    "date": "2025-12-16T16:43:35.711Z",
    "modified": "2025-12-16T16:43:35.711Z"
  },
  {
    "slug": "draftkings-casino-pa-promo",
    "type": "post",
    "title": "DraftKings Casino PA Promo (2025 Guide to Legal Pennsylvania Offers)",
    "date": "2025-12-16T16:33:56.905Z",
    "modified": "2025-12-16T16:33:56.905Z"
  },
  {
    "slug": "online-casino-games-new-jersey",
    "type": "post",
    "title": "Online Casino Games New Jersey (2025 Guide to Legal NJ Casino Games)",
    "date": "2025-12-16T09:41:58.589Z",
    "modified": "2025-12-16T09:41:58.589Z"
  },
  {
    "slug": "best-nj-online-casino",
    "type": "post",
    "title": "Best NJ Online Casino (2025 Guide to Legal & Safe New Jersey Casinos)",
    "date": "2025-12-16T09:30:08.930Z",
    "modified": "2025-12-16T09:30:08.930Z"
  },
  {
    "slug": "best-online-casino-bonus-nj",
    "type": "post",
    "title": "Best Online Casino Bonus NJ (2025 Guide to Legal New Jersey Casino Offers)",
    "date": "2025-12-16T09:16:41.473Z",
    "modified": "2025-12-16T09:16:41.473Z"
  },
  {
    "slug": "real-money-online-gambling-casinos-usa",
    "type": "post",
    "title": "Real Money Online Gambling Casinos USA (2025 Legal Guide & State-by-State Truth)",
    "date": "2025-12-16T09:02:46.264Z",
    "modified": "2025-12-16T09:02:46.264Z"
  },
  {
    "slug": "is-draftkings-casino-legal-in-florida",
    "type": "post",
    "title": "Is DraftKings Casino Legal in Florida? (2025 Legal Status Explained Clearly)",
    "date": "2025-12-16T08:33:55.838Z",
    "modified": "2025-12-16T08:33:55.838Z"
  },
  {
    "slug": "are-online-casinos-legal-in-florida",
    "type": "post",
    "title": "Are Online Casinos Legal in Florida? (2025 Complete Legal Gambling Guide)",
    "date": "2025-12-16T08:15:28.171Z",
    "modified": "2025-12-16T08:15:28.171Z"
  },
  {
    "slug": "are-casinos-legal-in-pennsylvania",
    "type": "post",
    "title": "Are Casinos Legal in Pennsylvania? (2025 Guide for Rivers Casino Poker Room Players)",
    "date": "2025-12-16T07:50:49.122Z",
    "modified": "2025-12-16T09:45:46.757Z"
  },
  {
    "slug": "rivers-casino-poker-room-chicago-hours",
    "type": "post",
    "title": "Rivers Casino Poker Room Chicago Hours: Real Hours, Closest Poker Room & What to Know (2025)",
    "date": "2025-12-15T21:14:29.127Z",
    "modified": "2025-12-16T07:53:17.647Z"
  },
  {
    "slug": "rivers-casino-des-plaines-address",
    "type": "post",
    "title": "Rivers Casino Des Plaines Address: Location, Directions & Poker Room Access (2025)",
    "date": "2025-12-15T20:50:15.763Z",
    "modified": "2025-12-16T07:53:40.208Z"
  },
  {
    "slug": "poker-at-rivers-casino",
    "type": "post",
    "title": "Poker at Rivers Casino: Locations, Games, Legality & Player Guide (2025)",
    "date": "2025-12-15T20:46:13.086Z",
    "modified": "2025-12-16T07:54:31.520Z"
  },
  {
    "slug": "poker-tournaments-rivers-casino",
    "type": "post",
    "title": "Poker Tournaments Rivers Casino: Locations, Formats & What Players Can Expect (2025)",
    "date": "2025-12-15T20:23:36.736Z",
    "modified": "2025-12-16T07:54:45.040Z"
  },
  {
    "slug": "rivers-casino-pittsburgh-poker-room",
    "type": "post",
    "title": "Rivers Casino Pittsburgh Poker Room: Tables, Games, Hours & What Players Should Know (2025)",
    "date": "2025-12-15T20:09:57.142Z",
    "modified": "2025-12-16T09:56:05.533Z"
  },
  {
    "slug": "rivers-casino-chicago-poker-room",
    "type": "post",
    "title": "Rivers Casino Chicago Poker Room: Does It Exist? Best Poker Options Near Chicago (2025)",
    "date": "2025-12-15T19:44:48.106Z",
    "modified": "2025-12-16T09:49:02.093Z"
  },
  {
    "slug": "rivers-casino-des-plaines-poker-room",
    "type": "post",
    "title": "Rivers Casino Des Plaines Poker Room: Games, Location, Tournaments & What to Expect (2025)",
    "date": "2025-12-15T19:22:16.225Z",
    "modified": "2025-12-16T09:53:09.141Z"
  },
  {
    "slug": "rivers-casino-poker-room",
    "type": "page",
    "title": "Rivers Casino Poker Room Guide (2025): Des Plaines, Chicago & Pittsburgh + Legal Online Casino Options",
    "date": "2025-12-15T18:20:17.115Z",
    "modified": "2025-12-16T07:19:58.059Z"
  },
  {
    "slug": "influencers-gone-wild",
    "type": "page",
    "title": "Influencers Gone Wild: The Dark Side of Online Fame",
    "date": "2025-12-15T14:47:23.316Z",
    "modified": "2025-12-15T16:22:55.634Z"
  },
  {
    "slug": "about",
    "type": "page",
    "title": "About Us | The Influencer Report",
    "date": "2025-12-15T14:36:06.791Z",
    "modified": "2025-12-15T16:21:00.512Z"
  },
  {
    "slug": "contact",
    "type": "page",
    "title": "Contact Us | The Influencer Report",
    "date": "2025-12-15T14:36:06.791Z",
    "modified": "2025-12-15T16:21:11.154Z"
  },
  {
    "slug": "disclaimer",
    "type": "page",
    "title": "Disclaimer | The Influencer Report",
    "date": "2025-12-15T14:36:06.791Z",
    "modified": "2025-12-15T16:21:23.045Z"
  },
  {
    "slug": "ethical-guidelines",
    "type": "page",
    "title": "Ethical Guidelines for Brands in Influencer Marketing | The Influencer Report",
    "date": "2025-12-15T14:36:06.791Z",
    "modified": "2025-12-15T16:21:31.700Z"
  },
  {
    "slug": "font",
    "type": "page",
    "title": "font",
    "date": "2025-12-15T14:36:06.791Z"
  },
  {
    "slug": "infamous-stunts",
    "type": "page",
    "title": "5 Infamous Influencer Stunts That Went Too Far | The Influencer Report",
    "date": "2025-12-15T14:36:06.791Z",
    "modified": "2025-12-15T16:21:42.667Z"
  },
  {
    "slug": "legal-consequences",
    "type": "page",
    "title": "Legal Consequences for Reckless Influencer Behavior | The Influencer Report",
    "date": "2025-12-15T14:36:06.791Z",
    "modified": "2025-12-15T16:21:51.266Z"
  },
  {
    "slug": "mental-health-crisis",
    "type": "page",
    "title": "The Mental Health Crisis in the Influencer Community | The Influencer Report",
    "date": "2025-12-15T14:36:06.791Z",
    "modified": "2025-12-15T16:22:00.843Z"
  },
  {
    "slug": "privacy-policy",
    "type": "page",
    "title": "Privacy Policy | The Influencer Report",
    "date": "2025-12-15T14:36:06.791Z",
    "modified": "2025-12-15T16:22:11.160Z"
  },
  {
    "slug": "terms-and-conditions",
    "type": "page",
    "title": "Terms & Conditions | The Influencer Report",
    "date": "2025-12-15T14:36:06.791Z",
    "modified": "2025-12-15T16:22:19.282Z"
  },
  {
    "slug": "tiktok-challenges",
    "type": "page",
    "title": "How Dangerous TikTok Challenges Affect Youth Culture | The Influencer Report",
    "date": "2025-12-15T14:36:06.791Z",
    "modified": "2025-12-15T16:22:29.292Z"
  },
  {
    "slug": "what-is-influencersgonewild",
    "type": "page",
    "title": "What is InfluencersGoneWild.com? An In-Depth Look | The Influencer Report",
    "date": "2025-12-15T14:36:06.791Z",
    "modified": "2025-12-15T16:22:39.696Z"
  }
]